{
  "enabled": true,
  "neededInstalledMods": [],
  "neededUninstalledMods": [],
  "spawns": [
    {
      "id": "landorus-1T",
      "pokemon": "landorus",
      "presets": [
        "natural"
      ],
      "type": "pokemon",
      "spawnablePositionType": "grounded",
      "bucket": "ultra-rare",
      "level": "50-70",
      "weight": 2.0,
      "condition": {
        "isRaining": false,
        "canSeeSky": true,
        "biomes": [
          "#cobblemon:is_savanna"
        ]
      }
    }
  ]
}